promptworkflows/PromptWorkflows.py
promptworkflows/__init__.py
promptworkflows-0.0.1.dist-info/METADATA
promptworkflows-0.0.1.dist-info/WHEEL
promptworkflows-0.0.1.dist-info/RECORD
